setup.cfg
setup.py
circle/__init__.py
circle/code.py
om286.egg-info/PKG-INFO
om286.egg-info/SOURCES.txt
om286.egg-info/dependency_links.txt
om286.egg-info/not-zip-safe
om286.egg-info/top_level.txt
square/__init__.py
square/code.py
triangle/__init__.py
triangle/code.py