Metadata-Version: 2.1
Name: om286
Version: 0.0
Summary: circle, triangle, square
Author-email: aenswpeo1@mozmail.com
